Metadata-Version: 1.1
Name: snimar-pycsw
Version: 2.1.2
Summary: pycsw implementation for the SNIMar project
Home-page: https://bitbucket.org/ipma/snimar_pycsw
Author: Pedro Dias
Author-email: pedro.dias@ipma.pt
License: MIT
Platform: all
Classifier: Development Status :: 5 - Production/Stable
Classifier: Environment :: Web Environment
Classifier: Intended Audience :: Developers
Classifier: Intended Audience :: Science/Research
Classifier: License :: OSI Approved :: MIT License
Classifier: Operating System :: OS Independent
Classifier: Programming Language :: Python
Classifier: Programming Language :: Python :: 2.6
Classifier: Programming Language :: Python :: 2.7
Classifier: Programming Language :: Python :: 3.4
Classifier: Topic :: Scientific/Engineering :: GIS
